{"name":"build-javascript","namedChunkGroups":{"app":{"name":"app","assets":[{"name":"webpack-runtime-1f11bbd8a4b7fb8210ba.js","size":6102},{"name":"framework-1ac93cd8000c4311fb77.js","size":210235},{"name":"app-545491b94328c8e7ee02.js","size":90717}],"filteredAssets":0,"assetsSize":307054,"filteredAuxiliaryAssets":3,"auxiliaryAssetsSize":776538},"component---src-pages-404-tsx":{"name":"component---src-pages-404-tsx","assets":[{"name":"styles.f0b7b84ad0e8a4f245ea.css","size":147007},{"name":"c16184b3-1b49df0b1e7d5219011e.js","size":2230},{"name":"2cca2479-cf64efe86dbcca44f9f3.js","size":3523},{"name":"commons-f537f61ffd60a999026d.js","size":160400},{"name":"component---src-pages-404-tsx-40df00c8cace58695efb.js","size":911}],"filteredAssets":0,"assetsSize":314071,"filteredAuxiliaryAssets":117,"auxiliaryAssetsSize":72183737},"component---src-pages-debug-redirects-tsx":{"name":"component---src-pages-debug-redirects-tsx","assets":[{"name":"styles.f0b7b84ad0e8a4f245ea.css","size":147007},{"name":"c16184b3-1b49df0b1e7d5219011e.js","size":2230},{"name":"2cca2479-cf64efe86dbcca44f9f3.js","size":3523},{"name":"commons-f537f61ffd60a999026d.js","size":160400},{"name":"component---src-pages-debug-redirects-tsx-95780ce6e63631f2bd11.js","size":1153}],"filteredAssets":0,"assetsSize":314313,"filteredAuxiliaryAssets":117,"auxiliaryAssetsSize":72185222},"component---src-pages-index-tsx":{"name":"component---src-pages-index-tsx","assets":[{"name":"styles.f0b7b84ad0e8a4f245ea.css","size":147007},{"name":"c16184b3-1b49df0b1e7d5219011e.js","size":2230},{"name":"2cca2479-cf64efe86dbcca44f9f3.js","size":3523},{"name":"75fc9c18-f71279181183774e258e.js","size":60483},{"name":"commons-f537f61ffd60a999026d.js","size":160400},{"name":"083fcf652479e2899573de2cb0d9a486b1ed95d5-47c0f2d790faa87edb72.js","size":15944},{"name":"b95451f0b310186e909e788b848f8c20c7036633-47a36eb907b3ba1da6a0.js","size":14077},{"name":"component---src-pages-index-tsx-bcc7c3f8eff56e47a167.js","size":1831}],"filteredAssets":0,"assetsSize":405495,"filteredAuxiliaryAssets":120,"auxiliaryAssetsSize":72638024},"component---src-pages-locations-tsx":{"name":"component---src-pages-locations-tsx","assets":[{"name":"styles.f0b7b84ad0e8a4f245ea.css","size":147007},{"name":"c16184b3-1b49df0b1e7d5219011e.js","size":2230},{"name":"2cca2479-cf64efe86dbcca44f9f3.js","size":3523},{"name":"commons-f537f61ffd60a999026d.js","size":160400},{"name":"083fcf652479e2899573de2cb0d9a486b1ed95d5-47c0f2d790faa87edb72.js","size":15944},{"name":"component---src-pages-locations-tsx-2b27ecd750548e08c6e6.js","size":876}],"filteredAssets":0,"assetsSize":329980,"filteredAuxiliaryAssets":118,"auxiliaryAssetsSize":72280170},"component---src-pages-posters-tsx":{"name":"component---src-pages-posters-tsx","assets":[{"name":"styles.f0b7b84ad0e8a4f245ea.css","size":147007},{"name":"c16184b3-1b49df0b1e7d5219011e.js","size":2230},{"name":"2cca2479-cf64efe86dbcca44f9f3.js","size":3523},{"name":"commons-f537f61ffd60a999026d.js","size":160400},{"name":"component---src-pages-posters-tsx-bad2ab9bb98aefe9f149.js","size":10568}],"filteredAssets":0,"assetsSize":323728,"filteredAuxiliaryAssets":117,"auxiliaryAssetsSize":72251059},"component---src-pages-speakers-tsx":{"name":"component---src-pages-speakers-tsx","assets":[{"name":"styles.f0b7b84ad0e8a4f245ea.css","size":147007},{"name":"c16184b3-1b49df0b1e7d5219011e.js","size":2230},{"name":"2cca2479-cf64efe86dbcca44f9f3.js","size":3523},{"name":"commons-f537f61ffd60a999026d.js","size":160400},{"name":"083fcf652479e2899573de2cb0d9a486b1ed95d5-47c0f2d790faa87edb72.js","size":15944},{"name":"component---src-pages-speakers-tsx-c309584ed597fba12705.js","size":834}],"filteredAssets":0,"assetsSize":329938,"filteredAuxiliaryAssets":118,"auxiliaryAssetsSize":72279864},"component---src-pages-tags-tsx":{"name":"component---src-pages-tags-tsx","assets":[{"name":"styles.f0b7b84ad0e8a4f245ea.css","size":147007},{"name":"c16184b3-1b49df0b1e7d5219011e.js","size":2230},{"name":"2cca2479-cf64efe86dbcca44f9f3.js","size":3523},{"name":"75fc9c18-f71279181183774e258e.js","size":60483},{"name":"commons-f537f61ffd60a999026d.js","size":160400},{"name":"083fcf652479e2899573de2cb0d9a486b1ed95d5-47c0f2d790faa87edb72.js","size":15944},{"name":"component---src-pages-tags-tsx-de6815ace04d21511f1e.js","size":3841}],"filteredAssets":0,"assetsSize":393428,"filteredAuxiliaryAssets":119,"auxiliaryAssetsSize":72563945},"component---src-pages-talks-tsx":{"name":"component---src-pages-talks-tsx","assets":[{"name":"styles.f0b7b84ad0e8a4f245ea.css","size":147007},{"name":"c16184b3-1b49df0b1e7d5219011e.js","size":2230},{"name":"2cca2479-cf64efe86dbcca44f9f3.js","size":3523},{"name":"75fc9c18-f71279181183774e258e.js","size":60483},{"name":"commons-f537f61ffd60a999026d.js","size":160400},{"name":"083fcf652479e2899573de2cb0d9a486b1ed95d5-47c0f2d790faa87edb72.js","size":15944},{"name":"component---src-pages-talks-tsx-6c74cdbede6dcb5bf616.js","size":3440}],"filteredAssets":0,"assetsSize":393027,"filteredAuxiliaryAssets":119,"auxiliaryAssetsSize":72563267},"component---src-pages-unterstuetzer-tsx":{"name":"component---src-pages-unterstuetzer-tsx","assets":[{"name":"styles.f0b7b84ad0e8a4f245ea.css","size":147007},{"name":"c16184b3-1b49df0b1e7d5219011e.js","size":2230},{"name":"2cca2479-cf64efe86dbcca44f9f3.js","size":3523},{"name":"commons-f537f61ffd60a999026d.js","size":160400},{"name":"component---src-pages-unterstuetzer-tsx-6c7946d35d5deec320db.js","size":15235}],"filteredAssets":0,"assetsSize":328395,"filteredAuxiliaryAssets":117,"auxiliaryAssetsSize":72254612},"component---src-templates-location-page-tsx":{"name":"component---src-templates-location-page-tsx","assets":[{"name":"styles.f0b7b84ad0e8a4f245ea.css","size":147007},{"name":"c16184b3-1b49df0b1e7d5219011e.js","size":2230},{"name":"2cca2479-cf64efe86dbcca44f9f3.js","size":3523},{"name":"commons-f537f61ffd60a999026d.js","size":160400},{"name":"component---src-templates-location-page-tsx-66f99d488944fe4e5e5a.js","size":1610}],"filteredAssets":0,"assetsSize":314770,"filteredAuxiliaryAssets":117,"auxiliaryAssetsSize":72186458},"component---src-templates-speaker-page-tsx":{"name":"component---src-templates-speaker-page-tsx","assets":[{"name":"styles.f0b7b84ad0e8a4f245ea.css","size":147007},{"name":"c16184b3-1b49df0b1e7d5219011e.js","size":2230},{"name":"2cca2479-cf64efe86dbcca44f9f3.js","size":3523},{"name":"commons-f537f61ffd60a999026d.js","size":160400},{"name":"component---src-templates-speaker-page-tsx-2b70a93379a65ecad731.js","size":10469}],"filteredAssets":0,"assetsSize":323629,"filteredAuxiliaryAssets":117,"auxiliaryAssetsSize":72251239},"component---src-templates-static-page-tsx":{"name":"component---src-templates-static-page-tsx","assets":[{"name":"styles.f0b7b84ad0e8a4f245ea.css","size":147007},{"name":"c16184b3-1b49df0b1e7d5219011e.js","size":2230},{"name":"2cca2479-cf64efe86dbcca44f9f3.js","size":3523},{"name":"commons-f537f61ffd60a999026d.js","size":160400},{"name":"component---src-templates-static-page-tsx-7e013f4f0cc0eabd4a50.js","size":933}],"filteredAssets":0,"assetsSize":314093,"filteredAuxiliaryAssets":117,"auxiliaryAssetsSize":72184140},"component---src-templates-talk-page-tsx":{"name":"component---src-templates-talk-page-tsx","assets":[{"name":"styles.f0b7b84ad0e8a4f245ea.css","size":147007},{"name":"c16184b3-1b49df0b1e7d5219011e.js","size":2230},{"name":"2cca2479-cf64efe86dbcca44f9f3.js","size":3523},{"name":"75fc9c18-f71279181183774e258e.js","size":60483},{"name":"commons-f537f61ffd60a999026d.js","size":160400},{"name":"083fcf652479e2899573de2cb0d9a486b1ed95d5-47c0f2d790faa87edb72.js","size":15944},{"name":"b95451f0b310186e909e788b848f8c20c7036633-47a36eb907b3ba1da6a0.js","size":14077},{"name":"component---src-templates-talk-page-tsx-ab69b6140103e09d919e.js","size":496}],"filteredAssets":0,"assetsSize":404160,"filteredAuxiliaryAssets":120,"auxiliaryAssetsSize":72631493}},"assetsByChunkName":{"app":["webpack-runtime-1f11bbd8a4b7fb8210ba.js","framework-1ac93cd8000c4311fb77.js","app-545491b94328c8e7ee02.js"],"component---src-pages-404-tsx":["styles.f0b7b84ad0e8a4f245ea.css","c16184b3-1b49df0b1e7d5219011e.js","2cca2479-cf64efe86dbcca44f9f3.js","commons-f537f61ffd60a999026d.js","component---src-pages-404-tsx-40df00c8cace58695efb.js"],"component---src-pages-debug-redirects-tsx":["styles.f0b7b84ad0e8a4f245ea.css","c16184b3-1b49df0b1e7d5219011e.js","2cca2479-cf64efe86dbcca44f9f3.js","commons-f537f61ffd60a999026d.js","component---src-pages-debug-redirects-tsx-95780ce6e63631f2bd11.js"],"component---src-pages-index-tsx":["styles.f0b7b84ad0e8a4f245ea.css","c16184b3-1b49df0b1e7d5219011e.js","2cca2479-cf64efe86dbcca44f9f3.js","75fc9c18-f71279181183774e258e.js","commons-f537f61ffd60a999026d.js","083fcf652479e2899573de2cb0d9a486b1ed95d5-47c0f2d790faa87edb72.js","b95451f0b310186e909e788b848f8c20c7036633-47a36eb907b3ba1da6a0.js","component---src-pages-index-tsx-bcc7c3f8eff56e47a167.js"],"component---src-pages-locations-tsx":["styles.f0b7b84ad0e8a4f245ea.css","c16184b3-1b49df0b1e7d5219011e.js","2cca2479-cf64efe86dbcca44f9f3.js","commons-f537f61ffd60a999026d.js","083fcf652479e2899573de2cb0d9a486b1ed95d5-47c0f2d790faa87edb72.js","component---src-pages-locations-tsx-2b27ecd750548e08c6e6.js"],"component---src-pages-posters-tsx":["styles.f0b7b84ad0e8a4f245ea.css","c16184b3-1b49df0b1e7d5219011e.js","2cca2479-cf64efe86dbcca44f9f3.js","commons-f537f61ffd60a999026d.js","component---src-pages-posters-tsx-bad2ab9bb98aefe9f149.js"],"component---src-pages-speakers-tsx":["styles.f0b7b84ad0e8a4f245ea.css","c16184b3-1b49df0b1e7d5219011e.js","2cca2479-cf64efe86dbcca44f9f3.js","commons-f537f61ffd60a999026d.js","083fcf652479e2899573de2cb0d9a486b1ed95d5-47c0f2d790faa87edb72.js","component---src-pages-speakers-tsx-c309584ed597fba12705.js"],"component---src-pages-tags-tsx":["styles.f0b7b84ad0e8a4f245ea.css","c16184b3-1b49df0b1e7d5219011e.js","2cca2479-cf64efe86dbcca44f9f3.js","75fc9c18-f71279181183774e258e.js","commons-f537f61ffd60a999026d.js","083fcf652479e2899573de2cb0d9a486b1ed95d5-47c0f2d790faa87edb72.js","component---src-pages-tags-tsx-de6815ace04d21511f1e.js"],"component---src-pages-talks-tsx":["styles.f0b7b84ad0e8a4f245ea.css","c16184b3-1b49df0b1e7d5219011e.js","2cca2479-cf64efe86dbcca44f9f3.js","75fc9c18-f71279181183774e258e.js","commons-f537f61ffd60a999026d.js","083fcf652479e2899573de2cb0d9a486b1ed95d5-47c0f2d790faa87edb72.js","component---src-pages-talks-tsx-6c74cdbede6dcb5bf616.js"],"component---src-pages-unterstuetzer-tsx":["styles.f0b7b84ad0e8a4f245ea.css","c16184b3-1b49df0b1e7d5219011e.js","2cca2479-cf64efe86dbcca44f9f3.js","commons-f537f61ffd60a999026d.js","component---src-pages-unterstuetzer-tsx-6c7946d35d5deec320db.js"],"component---src-templates-location-page-tsx":["styles.f0b7b84ad0e8a4f245ea.css","c16184b3-1b49df0b1e7d5219011e.js","2cca2479-cf64efe86dbcca44f9f3.js","commons-f537f61ffd60a999026d.js","component---src-templates-location-page-tsx-66f99d488944fe4e5e5a.js"],"component---src-templates-speaker-page-tsx":["styles.f0b7b84ad0e8a4f245ea.css","c16184b3-1b49df0b1e7d5219011e.js","2cca2479-cf64efe86dbcca44f9f3.js","commons-f537f61ffd60a999026d.js","component---src-templates-speaker-page-tsx-2b70a93379a65ecad731.js"],"component---src-templates-static-page-tsx":["styles.f0b7b84ad0e8a4f245ea.css","c16184b3-1b49df0b1e7d5219011e.js","2cca2479-cf64efe86dbcca44f9f3.js","commons-f537f61ffd60a999026d.js","component---src-templates-static-page-tsx-7e013f4f0cc0eabd4a50.js"],"component---src-templates-talk-page-tsx":["styles.f0b7b84ad0e8a4f245ea.css","c16184b3-1b49df0b1e7d5219011e.js","2cca2479-cf64efe86dbcca44f9f3.js","75fc9c18-f71279181183774e258e.js","commons-f537f61ffd60a999026d.js","083fcf652479e2899573de2cb0d9a486b1ed95d5-47c0f2d790faa87edb72.js","b95451f0b310186e909e788b848f8c20c7036633-47a36eb907b3ba1da6a0.js","component---src-templates-talk-page-tsx-ab69b6140103e09d919e.js"]},"childAssetsByChunkName":{}}