{"data":{"speaker":{"html":"<p>Wolfgang Weigend arbeitet als Sen. Leitender Systemberater bei der Oracle Deutschland B.V. &#x26; Co. KG. Er beschäftigt sich\nmit Java-Technologie und -Architektur für unternehmensweite Anwendungsentwicklung.</p>","fields":{"slug":"/speakers/wolfgang_weigend/"},"frontmatter":{"name":"Wolfgang Weigend","twitter_name":"wolflook","pic":"images/wolfgang_weigend.jpg"}},"talks":null},"pageContext":{"speakerSlug":"/speakers/wolfgang_weigend/","speakerId":"wolfgang_weigend"}}