{"data":{"markdownRemark":{"html":"<br/>\n<p>Die JUG macht Sommerpause. Im Juli gibt es deshalb keinen Vortrag.\nStattdessen gibt es wieder einen gemeinsamen <strong>JUG-Grill-Abend</strong> am Dienstag, 31. Juli.</p>\n<img style=\"width:500px\" alt=\"grillen\" src=\"https://github.com/juggr/grafiken/raw/master/Plakate/Plakat_2018_07/Plakat2018-07-01.png\"/>\n<p>Dazu treffen wir uns in den Räumlichkeiten des <a href=\"http://www.gr-kickerking.de/\">Görlitzer Kickerking e.V.</a>\nauf der <a href=\"https://goo.gl/maps/jx11ctvt5EN2\">Hospital-Straße 14</a>, wie immer ab 19 Uhr.</p>\n<img style=\"width:300px\" alt=\"kickerking logo\" src=\"/images/kickerking_logo.jpg\"/>\n<p>Bitte bringt Grillgut mit, welches ihr auf den Grill werfen wollt.\nGetränke können beim Kickerking-Verein erworben werden.\nDa der Verein seine Räumlichkeiten unter anderem auch durch Getränkeverkauf finanziert, und wir zu Gast sind,\nbitten wir euch, von selbst mitgebrachten Getränken abzusehen.</p>\n<p>Während und nach dem Grillen kann natürlich gerne gekickert werden.</p>\n<hr>\n<p>Datum: 31.07.2018, 19:00 Uhr</p>\n<p>Ort: Görlitzer Kickerking e.V., Hospital-Straße 14, 02826 Görlitz</p>","frontmatter":{"title":"JUG Sommerpause: Grillen"}}},"pageContext":{"slug":"/posts/2018-07-31-grillabend/"}}